followed/__init__.py
followed/_version.py
followed/tests/__init__.py
followed/tests/conftest.py
followed/tests/test_examples.py
followed/tests/test_helloworld.py
followed/tests/test_wraps.py
followed-0.0.3.dist-info/AUTHORS.rst
followed-0.0.3.dist-info/LICENSE
followed-0.0.3.dist-info/METADATA
followed-0.0.3.dist-info/WHEEL
followed-0.0.3.dist-info/entry_points.txt
followed-0.0.3.dist-info/top_level.txt
followed-0.0.3.dist-info/RECORD
